yfs/__init__.py
yfs/asset_types.py
yfs/cleaner.py
yfs/exchanges.py
yfs/lookup.py
yfs/multidownloader.py
yfs/options.py
yfs/paths.py
yfs/quote.py
yfs/requestor.py
yfs/statistics.py
yfs/summary.py
yfs-0.3.2.dist-info/LICENSE
yfs-0.3.2.dist-info/WHEEL
yfs-0.3.2.dist-info/METADATA
yfs-0.3.2.dist-info/RECORD
