Metadata-Version: 2.1
Name: yfs
Version: 0.3.2
Summary: Scrape Yahoo Finance
Home-page: https://dgnsrekt.github.io/yfs/
License: MIT
Keywords: yahoo,finance,scraper,yfs
Author: dgnsrekt
Author-email: dgnsrekt@pm.me
Requires-Python: >=3.8,<4.0
Classifier: License :: OSI Approved :: MIT License
Classifier: Programming Language :: Python :: 3
Classifier: Programming Language :: Python :: 3.8
Requires-Dist: enlighten (>=1.6.2,<2.0.0)
Requires-Dist: loguru (>=0.5.2,<0.6.0)
Requires-Dist: more_itertools (>=8.5.0,<9.0.0)
Requires-Dist: pandas (>=1.1.2,<2.0.0)
Requires-Dist: pendulum (>=2.1.2,<3.0.0)
Requires-Dist: prompt-toolkit (>=3.0.7,<4.0.0)
Requires-Dist: pydantic (>=1.6.1,<2.0.0)
Requires-Dist: python-decouple (>=3.3,<4.0)
Requires-Dist: requests-html (>=0.10.0,<0.11.0)
Requires-Dist: requests[socks] (>=2.24.0,<3.0.0)
Project-URL: Repository, https://github.com/dgnsrekt/yfs
